napari_indices/__init__.py
napari_indices/_reader.py
napari_indices/_sample_data.py
napari_indices/_widget.py
napari_indices/_writer.py
napari_indices/napari.yaml
napari_indices/_tests/__init__.py
napari_indices/_tests/test_reader.py
napari_indices/_tests/test_sample_data.py
napari_indices/_tests/test_widget.py
napari_indices/_tests/test_writer.py
napari_indices-0.0.2.dist-info/LICENSE
napari_indices-0.0.2.dist-info/METADATA
napari_indices-0.0.2.dist-info/WHEEL
napari_indices-0.0.2.dist-info/entry_points.txt
napari_indices-0.0.2.dist-info/top_level.txt
napari_indices-0.0.2.dist-info/RECORD
